behavysis_viewer/.DS_Store
behavysis_viewer/__init__.py
behavysis_viewer/__main__.py
behavysis_viewer/models/__init__.py
behavysis_viewer/models/bout_inspect_list_model.py
behavysis_viewer/models/bouts_list_model.py
behavysis_viewer/models/exp_file_manager.py
behavysis_viewer/models/keypoints_model.py
behavysis_viewer/models/vid_model.py
behavysis_viewer/resources/base_palette.xml
behavysis_viewer/ui/__init__.py
behavysis_viewer/ui/main_ui.py
behavysis_viewer/ui/main_ui.ui
behavysis_viewer/ui/settings_ui.py
behavysis_viewer/ui/settings_ui.ui
behavysis_viewer/utils/__init__.py
behavysis_viewer/utils/constants.py
behavysis_viewer/utils/cv2_qt_mixin.py
behavysis_viewer/widgets/__init__.py
behavysis_viewer/widgets/cv_view.py
behavysis_viewer/widgets/graph_view.py
behavysis_viewer/windows/__init__.py
behavysis_viewer/windows/help.py
behavysis_viewer/windows/main.py
behavysis_viewer/windows/settings.py
behavysis_viewer/windows/window_mixin.py
behavysis_viewer-0.1.24.dist-info/LICENSE
behavysis_viewer-0.1.24.dist-info/METADATA
behavysis_viewer-0.1.24.dist-info/WHEEL
behavysis_viewer-0.1.24.dist-info/entry_points.txt
behavysis_viewer-0.1.24.dist-info/RECORD
