Metadata-Version: 2.1
Name: behavysis_viewer
Version: 0.1.24
Summary: A semi-automated behaviour verification, processing and analysis package.
Home-page: https://tlee08.github.io/behavysis_viewer
License: LGPL-3.0-or-later
Author: BowenLab
Requires-Python: >=3.12,<3.13
Classifier: License :: OSI Approved :: GNU Lesser General Public License v3 or later (LGPLv3+)
Classifier: Programming Language :: Python :: 3
Classifier: Programming Language :: Python :: 3.12
Requires-Dist: PySide6 (>=6.8.0.2,<7.0.0.0)
Requires-Dist: behavysis_core (>=0.1.24,<0.2.0)
Requires-Dist: pyqtgraph (>=0.13.7,<0.14.0)
Project-URL: Repository, https://github.com/tlee08/behavysis_viewer
